exclude-nets/__init__.py
exclude-nets/__main__.py
exclude_nets/__init__.py
exclude_nets/__main__.py
exclude_nets-0.1.1.dist-info/LICENSE
exclude_nets-0.1.1.dist-info/METADATA
exclude_nets-0.1.1.dist-info/WHEEL
exclude_nets-0.1.1.dist-info/entry_points.txt
exclude_nets-0.1.1.dist-info/top_level.txt
exclude_nets-0.1.1.dist-info/RECORD
