Metadata-Version: 2.1
Name: exclude-nets
Version: 0.1.1
Summary: Exclude the given IPv4 networks.
Home-page: https://github.com/kerryeon/exclude-nets
Author: kerryeon
Author-email: great.ho.kim@gmail.com
License: UNKNOWN
Platform: UNKNOWN
Classifier: License :: OSI Approved :: MIT License
